decore_base/__init__.py
decore_base/decore.py
decore_base/globals.py
decore_base/classes/decore_action.py
decore_base/classes/decore_app.py
decore_base/classes/decore_base.py
decore_base/classes/decore_dialog.py
decore_base/classes/decore_element.py
decore_base/classes/decore_function.py
decore_base/classes/decore_list.py
decore_base/classes/decore_model.py
decore_base/classes/decore_object.py
decore_base/classes/decore_pool.py
decore_base/classes/decore_prompt.py
decore_base/classes/decore_query.py
decore_base/classes/decore_return.py
decore_base/classes/decore_translate.py
decore_base/classes/decore_view.py
decore_base/classes/decore_widget.py
decore_base/docs/social_header.txt
decore_base/extensions/conform_model.py
decore_base/extensions/perform_model.py
decore_base/extensions/reform_client_model.py
decore_base/extensions/reform_server_model.py
decore_base/extensions/depricated/askform_base.py
decore_base/extensions/depricated/buyform_base.py
decore_base/extensions/depricated/conform_base.py
decore_base/extensions/depricated/deform_base.py
decore_base/library/__init__.py
decore_base/library/powershell.py
decore_base/library/powershell2.py
decore_base/library/return_value.py
decore_base/library/particl_market/__init__.py
decore_base/library/particl_market/particl_market.py
decore_base/library/roaster/__init__.py
decore_base/library/roaster/roaster_client.py
decore_base/library/roaster/roaster_functions.py
decore_base/library/roaster/roaster_server.py
decore_base/prepare/.gitignore
decore_base/prepare/.vscode/launch.json
decore_base/prepare/spa/static/favicon.ico
decore_base/prepare/spa/static/css/912.77e6bcbe.css
decore_base/prepare/spa/static/css/app.d398f07d.css
decore_base/prepare/spa/static/css/vendor.14c9ac7a.css
decore_base/prepare/spa/static/fonts/KFOkCnqEu92Fr1MmgVxIIzQ.68bb21d0.woff
decore_base/prepare/spa/static/fonts/KFOlCnqEu92Fr1MmEU9fBBc-.48af7707.woff
decore_base/prepare/spa/static/fonts/KFOlCnqEu92Fr1MmSU5fBBc-.c2f7ab22.woff
decore_Base-0.12.dist-info/LICENSE
decore_Base-0.12.dist-info/METADATA
decore_Base-0.12.dist-info/WHEEL
decore_Base-0.12.dist-info/top_level.txt
decore_Base-0.12.dist-info/RECORD
