Metadata-Version: 2.1
Name: decore-Base
Version: 0.12
Summary: decore Base is a "Python to Vue.js" open source package that helps you go from idea to view in a few simple steps. It is targeted to those who want to focus on the results of their algorithms, do scientific work, perform promotional teaching or learning functions.
Home-page: https://github.com/KemoPanzah/decore_Base
Author: Kemo Panzah
Classifier: Programming Language :: Python :: 3
Classifier: License :: OSI Approved :: GNU General Public License v3 (GPLv3)
Classifier: Operating System :: Microsoft :: Windows
Requires-Python: >=3.9
License-File: LICENSE
Requires-Dist: argon2-cffi (==21.3.0)
Requires-Dist: argon2-cffi-bindings (==21.2.0)
Requires-Dist: blinker (==1.6.2)
Requires-Dist: Cerberus (==1.3.4)
Requires-Dist: certifi (==2023.5.7)
Requires-Dist: cffi (==1.15.1)
Requires-Dist: charset-normalizer (==3.1.0)
Requires-Dist: click (==8.1.3)
Requires-Dist: colorama (==0.4.6)
Requires-Dist: construct (==2.10.68)
Requires-Dist: coverage (==7.2.5)
Requires-Dist: dirsync (==2.2.5)
Requires-Dist: exceptiongroup (==1.1.1)
Requires-Dist: Flask (==2.3.2)
Requires-Dist: Flask-Cors (==3.0.10)
Requires-Dist: Flask-WTF (==1.1.1)
Requires-Dist: future (==0.18.3)
Requires-Dist: idna (==3.4)
Requires-Dist: importlib-metadata (==6.6.0)
Requires-Dist: iniconfig (==2.0.0)
Requires-Dist: itsdangerous (==2.1.2)
Requires-Dist: Jinja2 (==3.1.2)
Requires-Dist: libretranslatepy (==2.1.1)
Requires-Dist: lxml (==4.9.2)
Requires-Dist: MarkupSafe (==2.1.2)
Requires-Dist: mimesis (==9.0.0)
Requires-Dist: packaging (==23.1)
Requires-Dist: peewee (==3.16.2)
Requires-Dist: pluggy (==1.0.0)
Requires-Dist: pycparser (==2.21)
Requires-Dist: pycryptodomex (==3.17)
Requires-Dist: pykeepass (==4.0.3)
Requires-Dist: pytest (==7.3.1)
Requires-Dist: pytest-cov (==4.0.0)
Requires-Dist: python-dateutil (==2.8.2)
Requires-Dist: requests (==2.30.0)
Requires-Dist: six (==1.16.0)
Requires-Dist: str2type (==0.4.1)
Requires-Dist: tomli (==2.0.1)
Requires-Dist: translate (==3.6.1)
Requires-Dist: urllib3 (==2.0.2)
Requires-Dist: waitress (==2.1.2)
Requires-Dist: Werkzeug (==2.3.4)
Requires-Dist: WTForms (==3.0.1)
Requires-Dist: zipp (==3.15.0)
